meow/__init__.py
meow_uv-0.1.5.dist-info/METADATA
meow_uv-0.1.5.dist-info/WHEEL
meow_uv-0.1.5.dist-info/top_level.txt
meow_uv-0.1.5.dist-info/RECORD
