Metadata-Version: 2.1
Name: meow-uv
Version: 0.1.5
Summary: Determines if a string is a meow
Requires-Python: >=3.13
Requires-Dist: pytest>=8.3.4
